{"name":"build-javascript","namedChunkGroups":{"polyfill":{"name":"polyfill","assets":[{"name":"webpack-runtime-0ebc3716098dd6425f84.js","size":4360},{"name":"polyfill-f65558fe72ac600b21ce.js","size":85011}],"filteredAssets":0,"assetsSize":89371,"filteredAuxiliaryAssets":2,"auxiliaryAssetsSize":228448},"app":{"name":"app","assets":[{"name":"webpack-runtime-0ebc3716098dd6425f84.js","size":4360},{"name":"framework-45df31e08bbd8e79d801.js","size":141192},{"name":"app-8acaf81b7a0152876186.js","size":81691}],"filteredAssets":0,"assetsSize":227243,"filteredAuxiliaryAssets":3,"auxiliaryAssetsSize":710831},"component---src-pages-404-js":{"name":"component---src-pages-404-js","assets":[{"name":"component---src-pages-404-js-95e6271a6536725aa9fe.js","size":782}],"filteredAssets":0,"assetsSize":782,"filteredAuxiliaryAssets":1,"auxiliaryAssetsSize":1858},"component---src-pages-index-js":{"name":"component---src-pages-index-js","assets":[{"name":"framework-45df31e08bbd8e79d801.js","size":141192},{"name":"styles.d814718f785ad30c953e.css","size":207610},{"name":"component---src-pages-index-js-073656532cf92579fcff.js","size":214753}],"filteredAssets":0,"assetsSize":563555,"filteredAuxiliaryAssets":7,"auxiliaryAssetsSize":2744859}},"assetsByChunkName":{"polyfill":["webpack-runtime-0ebc3716098dd6425f84.js","polyfill-f65558fe72ac600b21ce.js"],"app":["webpack-runtime-0ebc3716098dd6425f84.js","framework-45df31e08bbd8e79d801.js","app-8acaf81b7a0152876186.js"],"component---src-pages-404-js":["component---src-pages-404-js-95e6271a6536725aa9fe.js"],"component---src-pages-index-js":["framework-45df31e08bbd8e79d801.js","styles.d814718f785ad30c953e.css","component---src-pages-index-js-073656532cf92579fcff.js"]},"childAssetsByChunkName":{}}